parladata_base_api/__init__py
parladata_base_api/api/__ini__.py
parladata_base_api/api/api.py
parladata_base_api/api/endpoints.py
parladata_base_api/storages/agenda_item_storage.py
parladata_base_api/storages/area_storage.py
parladata_base_api/storages/legislation_storage.py
parladata_base_api/storages/membership_storage.py
parladata_base_api/storages/organization_membership_storage.py
parladata_base_api/storages/organization_storage.py
parladata_base_api/storages/people_storage.py
parladata_base_api/storages/public_question_storage.py
parladata_base_api/storages/question_storage.py
parladata_base_api/storages/session_storage.py
parladata_base_api/storages/storage.py
parladata_base_api/storages/utils.py
parladata_base_api/storages/vote_storage.py
parladata_base_api-0.3.1.dist-info/METADATA
parladata_base_api-0.3.1.dist-info/WHEEL
parladata_base_api-0.3.1.dist-info/licenses/LICENSE.txt
parladata_base_api-0.3.1.dist-info/RECORD
