Metadata-Version: 2.4
Name: parladata-base-api
Version: 0.3.1
Summary: Cached api for parladata
Project-URL: Homepage, https://github.com/danesjenovdan/parladata_base_api
Project-URL: Issues, https://github.com/danesjenovdan/parladata_base_api/issues
Author-email: Danes je nov dan <tech@danesjenovdan.si>
License-File: LICENSE.txt
Classifier: Development Status :: 5 - Production/Stable
Classifier: Intended Audience :: Developers
Classifier: License :: CC0 1.0 Universal (CC0 1.0) Public Domain Dedication
Requires-Python: >=3.7
